hitips/Analysis.py
hitips/AnalysisGUI.py
hitips/BatchAnalyzer.py
hitips/Cell_Spot_Tracker.py
hitips/Display.py
hitips/DisplayGUI.py
hitips/GUI_parameters.py
hitips/GridLayout.py
hitips/HiTIPS.py
hitips/IO_ResourceGUI.py
hitips/InputOutput.py
hitips/MetaData_Reader.py
hitips/Roboto-Bold.ttf
hitips/Roboto-Light.ttf
hitips/__init__.py
hitips/bayesian_spot_tracking.py
hitips/cell_config.json
hitips/headless_configs.py
hitips/logging_decorator.py
hitips-1.1.4.dist-info/LICENSE.txt
hitips-1.1.4.dist-info/METADATA
hitips-1.1.4.dist-info/WHEEL
hitips-1.1.4.dist-info/entry_points.txt
hitips-1.1.4.dist-info/top_level.txt
hitips-1.1.4.dist-info/RECORD
