Metadata-Version: 2.1
Name: hitips
Version: 1.1.4
Summary: HiTIPS: High-Throughput Image Processing Software for FISH data analysis
Home-page: https://github.com/CBIIT/HiTIPS
Author: keikhosravi
Author-email: adib.keikhosravi@nih.gov
License: MIT
Keywords: high-throughput imaging FISH analysis cell segmentation signal quantification
Platform: UNKNOWN
Classifier: Programming Language :: Python :: 3
Classifier: License :: OSI Approved :: MIT License
Classifier: Operating System :: OS Independent
Classifier: Intended Audience :: Science/Research
Classifier: Topic :: Scientific/Engineering :: Image Processing
Requires-Python: >=3.9
License-File: LICENSE.txt
Requires-Dist: numpy (==1.23.5)
Requires-Dist: scikit-image (==0.18.3)
Requires-Dist: scipy (==1.11.3)
Requires-Dist: Pillow (==9.0.1)
Requires-Dist: pandas (==1.4.2)
Requires-Dist: matplotlib (==3.5.1)
Requires-Dist: btrack (==0.4.3)
Requires-Dist: imageio (==2.31.5)
Requires-Dist: tifffile (==2023.9.26)
Requires-Dist: aicsimageio (==4.7.0)
Requires-Dist: scikit-learn (==1.1.1)
Requires-Dist: hmmlearn (==0.3.0)
Requires-Dist: PyQt5 (==5.15.10)
Requires-Dist: cellpose (==2.0.5)
Requires-Dist: tensorflow (==2.8.4)
Requires-Dist: dask (==2022.2.1)
Requires-Dist: nd2reader (==3.3.0)
Requires-Dist: imaris-ims-file-reader (==0.1.8)
Requires-Dist: qimage2ndarray (==1.9.0)
Requires-Dist: spatial-efd (==1.2.1)
Requires-Dist: pydantic (==1.10.9)
Requires-Dist: aicspylibczi (==3.1.2)
Requires-Dist: opencv-python-headless (==4.9.0.80)
